<?xml version="1.0" encoding="UTF-8"?>
<log>
  <Entry1>
  <Date>2020-03-21</Date>
  <Time>15:32:16</Time>
  <Description>1</Description>
  <FileName>( Wszystkie )/Błogosławieństwo (The Blessing)</FileName>
  <title>Błogosławieństwo (The Blessing)</title>
  <author/>
  <ccli/>
  <HasChords>false</HasChords></Entry1>
  <Entry2>
  <Date>2020-03-21</Date>
  <Time>15:40:10</Time>
  <Description>3</Description>
  <FileName>( Wszystkie )/Błogosławieństwo (The Blessing)</FileName>
  <title>Błogosławieństwo (The Blessing)</title>
  <author/>
  <ccli/>
  <HasChords>true</HasChords></Entry2>
  <Entry3>
  <Date>2020-03-21</Date>
  <Time>15:41:51</Time>
  <Description>3</Description>
  <FileName>( Wszystkie )/Błogosławieństwo (The Blessing)</FileName>
  <title>Błogosławieństwo (The Blessing)</title>
  <author/>
  <ccli/>
  <HasChords>true</HasChords></Entry3>
  <Entry4>
  <Date>2020-03-21</Date>
  <Time>15:43:09</Time>
  <Description>3</Description>
  <FileName>( Wszystkie )/Błogosławieństwo (The Blessing)</FileName>
  <title>Błogosławieństwo (The Blessing)</title>
  <author/>
  <ccli/>
  <HasChords>true</HasChords></Entry4>
  <Entry5>
  <Date>2020-03-21</Date>
  <Time>15:43:14</Time>
  <Description>3</Description>
  <FileName>( Wszystkie )/Błogosławieństwo (The Blessing)</FileName>
  <title>Błogosławieństwo (The Blessing)</title>
  <author/>
  <ccli/>
  <HasChords>true</HasChords></Entry5>
  <Entry6>
  <Date>2020-04-23</Date>
  <Time>08:51:24</Time>
  <Description>1</Description>
  <FileName>( Wszystkie )/Jesteś tu (Way Maker)</FileName>
  <title>Jesteś tu (Way Maker)</title>
  <author/>
  <ccli/>
  <HasChords>false</HasChords></Entry6>
  <Entry7>
  <Date>2020-04-23</Date>
  <Time>08:52:24</Time>
  <Description>3</Description>
  <FileName>( Wszystkie )/Jesteś tu (Way Maker)</FileName>
  <title>Jesteś tu (Way Maker)</title>
  <author/>
  <ccli/>
  <HasChords>false</HasChords></Entry7>
  <Entry8>
  <Date>2020-04-23</Date>
  <Time>08:56:11</Time>
  <Description>3</Description>
  <FileName>( Wszystkie )/Jesteś tu (Way Maker)</FileName>
  <title>Jesteś tu (Way Maker)</title>
  <author/>
  <ccli/>
  <HasChords>true</HasChords></Entry8>
  <Entry9>
  <Date>2020-04-23</Date>
  <Time>08:57:09</Time>
  <Description>3</Description>
  <FileName>( Wszystkie )/Jesteś tu (Way Maker)</FileName>
  <title>Jesteś tu (Way Maker)</title>
  <author/>
  <ccli/>
  <HasChords>true</HasChords></Entry9>
  <Entry10>
  <Date>2020-08-15</Date>
  <Time>07:45:56</Time>
  <Description>1</Description>
  <FileName>( Wszystkie )/Dla Ciebie Żyć</FileName>
  <title>Dla Ciebie Żyć</title>
  <author/>
  <ccli/>
  <HasChords>false</HasChords></Entry10>
  <Entry11>
  <Date>2020-08-15</Date>
  <Time>07:46:16</Time>
  <Description>7</Description>
  <FileName>( Wszystkie )/Dla Ciebie Żyć (Build My Life)</FileName>
  <title>Dla Ciebie Żyć</title>
  <author/>
  <ccli/>
  <HasChords>false</HasChords></Entry11>
  <Entry12>
  <Date>2020-08-15</Date>
  <Time>07:47:25</Time>
  <Description>3</Description>
  <FileName>( Wszystkie )/Dla Ciebie Żyć (Build My Life)</FileName>
  <title>Dla Ciebie Żyć</title>
  <author/>
  <ccli/>
  <HasChords>false</HasChords></Entry12>
  <Entry13>
  <Date>2020-08-15</Date>
  <Time>09:33:18</Time>
  <Description>3</Description>
  <FileName>( Wszystkie )/Dla Ciebie Żyć (Build My Life)</FileName>
  <title>Dla Ciebie Żyć</title>
  <author/>
  <ccli/>
  <HasChords>true</HasChords></Entry13>
  <Entry14>
  <Date>2020-08-15</Date>
  <Time>09:34:57</Time>
  <Description>3</Description>
  <FileName>( Wszystkie )/Dla Ciebie Żyć (Build My Life)</FileName>
  <title>Dla Ciebie Żyć</title>
  <author/>
  <ccli/>
  <HasChords>true</HasChords></Entry14>
  <Entry15>
  <Date>2020-08-27</Date>
  <Time>11:46:51</Time>
  <Description>3</Description>
  <FileName>W</FileName>
  <title>Wasz Pan drogę zna</title>
  <author/>
  <ccli/>
  <HasChords>true</HasChords></Entry15>
  <Entry16>
  <Date>2020-08-27</Date>
  <Time>12:05:45</Time>
  <Description>1</Description>
  <FileName>( Wszystkie )/Po prostu z Jezuem żyć</FileName>
  <title>Po prostu z Jezuem żyć</title>
  <author/>
  <ccli/>
  <HasChords>false</HasChords></Entry16>
  <Entry17>
  <Date>2020-08-27</Date>
  <Time>12:15:13</Time>
  <Description>3</Description>
  <FileName>( Wszystkie )/Po prostu z Jezuem żyć</FileName>
  <title>Po prostu z Jezuem żyć</title>
  <author/>
  <ccli/>
  <HasChords>true</HasChords></Entry17>
  <Entry18>
  <Date>2020-08-27</Date>
  <Time>12:17:14</Time>
  <Description>3</Description>
  <FileName>( Wszystkie )/Po prostu z Jezuem żyć</FileName>
  <title>Po prostu z Jezuem żyć</title>
  <author/>
  <ccli/>
  <HasChords>true</HasChords></Entry18>
  <Entry19>
  <Date>2020-08-27</Date>
  <Time>12:23:35</Time>
  <Description>3</Description>
  <FileName>( Wszystkie )/Po prostu z Jezuem żyć</FileName>
  <title>Po prostu z Jezuem żyć</title>
  <author/>
  <ccli/>
  <HasChords>true</HasChords></Entry19>
  <Entry20>
  <Date>2020-09-08</Date>
  <Time>20:19:12</Time>
  <Description>1</Description>
  <FileName>( Wszystkie )/Bóg Przebudzenia (God Of Revival)</FileName>
  <title>Bóg Przebudzenia (God Of Revival)</title>
  <author/>
  <ccli/>
  <HasChords>false</HasChords></Entry20>
  <Entry21>
  <Date>2020-09-08</Date>
  <Time>20:20:05</Time>
  <Description>3</Description>
  <FileName>( Wszystkie )/Bóg Przebudzenia (God Of Revival)</FileName>
  <title>Bóg Przebudzenia (God Of Revival)</title>
  <author/>
  <ccli/>
  <HasChords>false</HasChords></Entry21>
  <Entry22>
  <Date>2020-09-08</Date>
  <Time>20:36:24</Time>
  <Description>3</Description>
  <FileName>( Wszystkie )/Bóg Przebudzenia (God Of Revival)</FileName>
  <title>Bóg Przebudzenia (God Of Revival)</title>
  <author/>
  <ccli/>
  <HasChords>true</HasChords></Entry22>
  <Entry23>
  <Date>2020-09-08</Date>
  <Time>20:44:24</Time>
  <Description>3</Description>
  <FileName>( Wszystkie )/Bóg Przebudzenia (God Of Revival)</FileName>
  <title>Bóg Przebudzenia (God Of Revival)</title>
  <author/>
  <ccli/>
  <HasChords>true</HasChords></Entry23>
  <Entry24>
  <Date>2020-09-09</Date>
  <Time>10:24:48</Time>
  <Description>3</Description>
  <FileName>( Wszystkie )/Bóg Przebudzenia (God Of Revival)</FileName>
  <title>Bóg Przebudzenia (God Of Revival)</title>
  <author/>
  <ccli/>
  <HasChords>true</HasChords></Entry24>
  <Entry25>
  <Date>2020-09-17</Date>
  <Time>10:52:52</Time>
  <Description>3</Description>
  <FileName>P</FileName>
  <title>Powietrzem moim jest</title>
  <author/>
  <ccli/>
  <HasChords>true</HasChords></Entry25>
  <Entry26>
  <Date>2020-09-17</Date>
  <Time>10:53:47</Time>
  <Description>3</Description>
  <FileName>P</FileName>
  <title>Powietrzem moim jest</title>
  <author/>
  <ccli/>
  <HasChords>true</HasChords></Entry26>
  <Entry27>
  <Date>2020-09-17</Date>
  <Time>10:55:40</Time>
  <Description>3</Description>
  <FileName>P</FileName>
  <title>Powietrzem moim jest</title>
  <author/>
  <ccli/>
  <HasChords>true</HasChords></Entry27>
  <Entry28>
  <Date>2020-09-17</Date>
  <Time>10:57:37</Time>
  <Description>3</Description>
  <FileName>P</FileName>
  <title>Powietrzem moim jest</title>
  <author/>
  <ccli/>
  <HasChords>true</HasChords></Entry28>
  <Entry29>
  <Date>2020-09-17</Date>
  <Time>11:02:43</Time>
  <Description>3</Description>
  <FileName>P</FileName>
  <title>Powietrzem moim jest</title>
  <author/>
  <ccli/>
  <HasChords>true</HasChords></Entry29>
  <Entry30>
  <Date>2020-09-21</Date>
  <Time>12:53:13</Time>
  <Description>1</Description>
  <FileName>( Wszystkie )/Czyste Serce (Clean)</FileName>
  <title>Czyste Serce (Clean)</title>
  <author></author>
  <ccli></ccli>
  <HasChords>false</HasChords></Entry30>
  <Entry31>
  <Date>2020-09-21</Date>
  <Time>12:53:37</Time>
  <Description>3</Description>
  <FileName>( Wszystkie )/Czyste Serce (Clean)</FileName>
  <title>Czyste Serce (Clean)</title>
  <author></author>
  <ccli></ccli>
  <HasChords>false</HasChords></Entry31>
  <Entry32>
  <Date>2020-09-21</Date>
  <Time>12:59:27</Time>
  <Description>3</Description>
  <FileName>( Wszystkie )/Czyste Serce (Clean)</FileName>
  <title>Czyste Serce (Clean)</title>
  <author></author>
  <ccli></ccli>
  <HasChords>true</HasChords></Entry32></log>